{"XM": {"time_data": {"2021-01-28": {"closing_price": "45.500000"}, "2021-01-29": {"closing_price": "44.000000"}, "2021-02-01": {"closing_price": "49.000000"}, "2021-02-02": {"closing_price": "51.250000"}, "2021-02-03": {"closing_price": "53.500000"}, "2021-02-04": {"closing_price": "54.900002"}, "2021-02-05": {"closing_price": "55.240002"}, "2021-02-08": {"closing_price": "50.500000"}, "2021-02-09": {"closing_price": "48.290001"}, "2021-02-10": {"closing_price": "46.000000"}, "2021-02-11": {"closing_price": "46.110001"}, "2021-02-12": {"closing_price": "45.360001"}}}}